{"2023-07-16":[{"time":"2023-07-16 12:51:31","path":"\/","client-address":"::1"},{"time":"2023-07-16 12:55:16","path":"\/","client-address":"::1"},{"time":"2023-07-16 12:57:48","path":"\/","client-address":"::1"},{"time":"2023-07-16 12:59:54","path":"\/","client-address":"::1"},{"time":"2023-07-16 13:01:00","path":"\/","client-address":"::1"},{"time":"2023-07-16 13:02:29","path":"\/","client-address":"::1"},{"time":"2023-07-16 13:02:42","path":"\/","client-address":"::1"},{"time":"2023-07-16 13:02:55","path":"\/","client-address":"::1"},{"time":"2023-07-16 13:07:23","path":"\/","client-address":"::1"},{"time":"2023-07-16 13:07:58","path":"\/","client-address":"::1"},{"time":"2023-07-16 13:18:36","path":"\/64b3ede53bb23","client-address":"::1"},{"time":"2023-07-16 13:18:47","path":"\/64b3ede53bb23","client-address":"::1"},{"time":"2023-07-16 13:21:37","path":"\/64b3ee67b98ad","client-address":"::1"},{"time":"2023-07-16 13:22:15","path":"\/64b3ee67b98ad","client-address":"::1"},{"time":"2023-07-16 13:22:31","path":"\/64b3ee67b98ad","client-address":"::1"},{"time":"2023-07-16 13:22:35","path":"\/64b3ee67b98ad","client-address":"::1"},{"time":"2023-07-16 13:23:53","path":"\/","client-address":"::1"},{"time":"2023-07-16 13:23:55","path":"\/","client-address":"::1"},{"time":"2023-07-16 13:24:00","path":"\/my-page","client-address":"::1"}]}